singlestroke/__init__.py
singlestroke/singlestroke.py
vpype_singlestroke-0.2.0.dist-info/licenses/LICENSE
vpype_singlestroke-0.2.0.dist-info/METADATA
vpype_singlestroke-0.2.0.dist-info/WHEEL
vpype_singlestroke-0.2.0.dist-info/entry_points.txt
vpype_singlestroke-0.2.0.dist-info/top_level.txt
vpype_singlestroke-0.2.0.dist-info/RECORD
