Metadata-Version: 2.4
Name: vpype-singlestroke
Version: 0.2.0
Summary: vpype plugin to convert closed paths to single-stroke open paths
Home-page: https://github.com/d-n-l-lab/singlestroke
Author: Dominik Lang
Classifier: Development Status :: 4 - Beta
Classifier: License :: OSI Approved :: MIT License
Classifier: Topic :: Multimedia :: Graphics
Classifier: Environment :: Plugins
License-File: LICENSE
Requires-Dist: vpype<2.0,>=1.9
Requires-Dist: click
Requires-Dist: numpy
Dynamic: author
Dynamic: classifier
Dynamic: description
Dynamic: description-content-type
Dynamic: home-page
Dynamic: license-file
Dynamic: requires-dist
Dynamic: summary
